OPCTree/__init__.py
OPCTree/example_filters.py
OPCTree/gen_structs.py
OPCTree/opc_extract.py
OPCTree/opc_fetch.py
OPCTree/opc_obj.py
OPCTree/opc_vars.py
OPCTree/settings.py
OPCTree/struct_identi.py
OPCTree/opc_class_lib/BasicLib_1_8_5.py
OPCTree/opc_class_lib/System.py
OPCTree/opc_class_lib/__init__.py
OPCTree/visualize/__init__.py
opctree-1.1.3.dist-info/licenses/LICENSE
opctree-1.1.3.dist-info/METADATA
opctree-1.1.3.dist-info/WHEEL
opctree-1.1.3.dist-info/top_level.txt
opctree-1.1.3.dist-info/RECORD
