Metadata-Version: 2.4
Name: OPCTree
Version: 1.1.3
Summary: A tool for efficient CLI handling of OPC DA structures
Author-email: Per Johnsson <perjohns@gmail.com>
License: Proprietary
Project-URL: Homepage, https://github.com/PerEAJ/OPCTree
Project-URL: Issues, https://github.com/PerEAJ/OPCTree/issues
Classifier: Programming Language :: Python :: 3
Classifier: Operating System :: OS Independent
Requires-Python: >=3.9
License-File: LICENSE
Requires-Dist: et_xmlfile==2.0.0
Requires-Dist: openpyxl==3.1.5
Requires-Dist: pywin32==310
Requires-Dist: OpenOPC-DA>=1.5.1
Dynamic: license-file
